<?xml version="1.0" encoding="utf-8"?>
<extension version="3.0" type="plugin" group="k2" method="upgrade">
	<name>Spoudazo Before Set SQL Query K2 Plugin</name>
	<author>YES Internet</author>
	<creationDate>June, 2015</creationDate>
	<copyright></copyright>
	<authorEmail>indo@yesinternet.gr</authorEmail>
	<authorUrl>www.yesinternet.gr</authorUrl>
	<version>1.0.0</version>
	<license>http://www.gnu.org/licenses/gpl-2.0.html GNU/GPL</license>
	<description>This plugin modifies K2 SQL queries</description>
	<files>
		<filename plugin="onbeforesetquery">onbeforesetquery.php</filename>
	</files>
</extension>